{"schemaVersion":1,"asOf":"2026-06-07T11:51:34.667Z","epoch":23207,"block":8354554,"stale":false,"source":"taostats","totalSubnets":129,"subnets":[{"uid":0,"name":"Root","emissionShare":0,"alphaPrice":1,"marketCap":6060034.662491354,"validators":8,"miners":27,"realRevenueSignal":0.115234375,"signalSource":"computed:v1-low-confidence","registeredAtBlock":null},{"uid":1,"name":"Apex","emissionShare":0,"alphaPrice":0.00936386,"marketCap":41850.622663191,"validators":8,"miners":4,"realRevenueSignal":0.0703125,"signalSource":"computed:v1-low-confidence","registeredAtBlock":172898},{"uid":2,"name":"DSperse","emissionShare":0,"alphaPrice":0.005183515,"marketCap":23576.473086033,"validators":9,"miners":3,"realRevenueSignal":0.076171875,"signalSource":"computed:v1-low-confidence","registeredAtBlock":2734060},{"uid":3,"name":"deprecated","emissionShare":0,"alphaPrice":0.02261088,"marketCap":105409.430351626,"validators":1,"miners":5,"realRevenueSignal":0.017578125,"signalSource":"computed:v1-low-confidence","registeredAtBlock":4165565},{"uid":4,"name":"Targon","emissionShare":0,"alphaPrice":0.052893199,"marketCap":257189.127220473,"validators":5,"miners":4,"realRevenueSignal":0.046875,"signalSource":"computed:v1-low-confidence","registeredAtBlock":1411451},{"uid":5,"name":"Hone","emissionShare":0,"alphaPrice":0.017385461,"marketCap":64851.516954721,"validators":12,"miners":1,"realRevenueSignal":0.095703125,"signalSource":"computed:v1-low-confidence","registeredAtBlock":2491604},{"uid":6,"name":"Numinous","emissionShare":0,"alphaPrice":0.003829864,"marketCap":18668.065541442,"validators":11,"miners":203,"realRevenueSignal":0.482421875,"signalSource":"computed:v1-low-confidence","registeredAtBlock":3219949},{"uid":7,"name":"Allways","emissionShare":0,"alphaPrice":0.00383255,"marketCap":18117.146739199,"validators":13,"miners":10,"realRevenueSignal":0.12109375,"signalSource":"computed:v1-low-confidence","registeredAtBlock":2627691},{"uid":8,"name":"Vanta","emissionShare":0,"alphaPrice":0.030312931,"marketCap":140188.147844315,"validators":17,"miners":41,"realRevenueSignal":0.212890625,"signalSource":"computed:v1-low-confidence","registeredAtBlock":1477264},{"uid":9,"name":"iota","emissionShare":0,"alphaPrice":0.035698725,"marketCap":154164.933366451,"validators":11,"miners":2,"realRevenueSignal":0.3234383171363854,"signalSource":"computed:v1","registeredAtBlock":1489797},{"uid":10,"name":"Swap","emissionShare":0,"alphaPrice":0.005459426,"marketCap":25642.166250647,"validators":15,"miners":1,"realRevenueSignal":0.119140625,"signalSource":"computed:v1-low-confidence","registeredAtBlock":2869647},{"uid":11,"name":"TrajectoryRL","emissionShare":0,"alphaPrice":0.009586102,"marketCap":39069.575624346,"validators":9,"miners":2,"realRevenueSignal":0.07421875,"signalSource":"computed:v1-low-confidence","registeredAtBlock":2918568},{"uid":12,"name":"Compute Horde","emissionShare":0,"alphaPrice":0.005828095,"marketCap":24277.221306736,"validators":6,"miners":8,"realRevenueSignal":0.0625,"signalSource":"computed:v1-low-confidence","registeredAtBlock":2256433},{"uid":13,"name":"Data Universe","emissionShare":0,"alphaPrice":0.007178701,"marketCap":34734.822769409,"validators":11,"miners":224,"realRevenueSignal":0.5234375,"signalSource":"computed:v1-low-confidence","registeredAtBlock":1907637},{"uid":14,"name":"Cacheon","emissionShare":0,"alphaPrice":0.012357841,"marketCap":51324.037332652,"validators":6,"miners":2,"realRevenueSignal":0.05078125,"signalSource":"computed:v1-low-confidence","registeredAtBlock":4848444},{"uid":15,"name":"ORO","emissionShare":0.06911744457577815,"alphaPrice":0.03309609,"marketCap":28213.289020572,"validators":12,"miners":102,"realRevenueSignal":0.7171875,"signalSource":"computed:v1","registeredAtBlock":7366897},{"uid":16,"name":"BitAds","emissionShare":0,"alphaPrice":0.003207587,"marketCap":13536.654526776,"validators":14,"miners":17,"realRevenueSignal":0.142578125,"signalSource":"computed:v1-low-confidence","registeredAtBlock":2765446},{"uid":17,"name":"404—GEN","emissionShare":0,"alphaPrice":0.010107552,"marketCap":49086.637475614,"validators":7,"miners":2,"realRevenueSignal":0.05859375,"signalSource":"computed:v1-low-confidence","registeredAtBlock":2840556},{"uid":18,"name":"Zeus","emissionShare":0.02047543946347548,"alphaPrice":0.007991027,"marketCap":37594.562306989,"validators":10,"miners":25,"realRevenueSignal":0.65078125,"signalSource":"computed:v1","registeredAtBlock":1604679},{"uid":19,"name":"blockmachine","emissionShare":0,"alphaPrice":0.01206099,"marketCap":52920.573960116,"validators":8,"miners":21,"realRevenueSignal":0.103515625,"signalSource":"computed:v1-low-confidence","registeredAtBlock":1956072},{"uid":20,"name":"GroundLayer","emissionShare":0,"alphaPrice":0.003641705,"marketCap":14637.517072959,"validators":12,"miners":1,"realRevenueSignal":0.095703125,"signalSource":"computed:v1-low-confidence","registeredAtBlock":1970929},{"uid":21,"name":"AdTAO","emissionShare":0,"alphaPrice":0.00363355,"marketCap":16528.896350159,"validators":11,"miners":1,"realRevenueSignal":0.087890625,"signalSource":"computed:v1-low-confidence","registeredAtBlock":3156578},{"uid":22,"name":"Desearch","emissionShare":0,"alphaPrice":0.004236334,"marketCap":18088.068966621,"validators":14,"miners":42,"realRevenueSignal":0.19140625,"signalSource":"computed:v1-low-confidence","registeredAtBlock":2009702},{"uid":23,"name":"Trishool","emissionShare":0,"alphaPrice":0.003881617,"marketCap":16492.030954449,"validators":12,"miners":1,"realRevenueSignal":0.095703125,"signalSource":"computed:v1-low-confidence","registeredAtBlock":2063528},{"uid":24,"name":"Quasar","emissionShare":0,"alphaPrice":0.008257192,"marketCap":38426.420741736,"validators":5,"miners":2,"realRevenueSignal":0.04296875,"signalSource":"computed:v1-low-confidence","registeredAtBlock":2538424},{"uid":25,"name":"Mainframe","emissionShare":0,"alphaPrice":0.004069828,"marketCap":18592.930713291,"validators":13,"miners":1,"realRevenueSignal":0.103515625,"signalSource":"computed:v1-low-confidence","registeredAtBlock":2998801},{"uid":26,"name":"Perturb","emissionShare":0.024633567735821975,"alphaPrice":0.009518405,"marketCap":7480.43112568,"validators":1,"miners":5,"realRevenueSignal":0.60703125,"signalSource":"computed:v1","registeredAtBlock":8123781},{"uid":27,"name":"Nodexo","emissionShare":0,"alphaPrice":0.003616709,"marketCap":15714.268328826,"validators":16,"miners":1,"realRevenueSignal":0.126953125,"signalSource":"computed:v1-low-confidence","registeredAtBlock":1727132},{"uid":28,"name":"gm","emissionShare":0,"alphaPrice":0.013582209,"marketCap":55312.863336814,"validators":13,"miners":1,"realRevenueSignal":0.103515625,"signalSource":"computed:v1-low-confidence","registeredAtBlock":4878363},{"uid":29,"name":"Coldint","emissionShare":0,"alphaPrice":0.00337388,"marketCap":15687.978773916,"validators":8,"miners":1,"realRevenueSignal":0.064453125,"signalSource":"computed:v1-low-confidence","registeredAtBlock":3379782},{"uid":30,"name":"Endure Network","emissionShare":0,"alphaPrice":0.00489841,"marketCap":23067.562624357,"validators":11,"miners":1,"realRevenueSignal":0.087890625,"signalSource":"computed:v1-low-confidence","registeredAtBlock":3250216},{"uid":31,"name":"Recall","emissionShare":0.004202268325182644,"alphaPrice":0.004607154,"marketCap":4736.368864654,"validators":15,"miners":1,"realRevenueSignal":0.547338592334145,"signalSource":"computed:v1","registeredAtBlock":7173591},{"uid":32,"name":"ItsAI","emissionShare":0,"alphaPrice":0.003834477,"marketCap":20133.046927857,"validators":6,"miners":182,"realRevenueSignal":0.40234375,"signalSource":"computed:v1-low-confidence","registeredAtBlock":2515294},{"uid":33,"name":"ReadyAI","emissionShare":0,"alphaPrice":0.007365752,"marketCap":30116.542247017,"validators":13,"miners":239,"realRevenueSignal":0.568359375,"signalSource":"computed:v1-low-confidence","registeredAtBlock":2943950},{"uid":34,"name":"BitMind","emissionShare":0,"alphaPrice":0.013017152,"marketCap":59109.65907127,"validators":7,"miners":30,"realRevenueSignal":0.11328125,"signalSource":"computed:v1-low-confidence","registeredAtBlock":3493948},{"uid":35,"name":"OxMarkets","emissionShare":0,"alphaPrice":0.004539852,"marketCap":22550.027946748,"validators":11,"miners":3,"realRevenueSignal":0.091796875,"signalSource":"computed:v1-low-confidence","registeredAtBlock":3037158},{"uid":36,"name":"Eirel","emissionShare":0.012103537650734783,"alphaPrice":0.006413552,"marketCap":3209.058805454,"validators":8,"miners":1,"realRevenueSignal":0.62578125,"signalSource":"computed:v1","registeredAtBlock":7894898},{"uid":37,"name":"Aurelius","emissionShare":0,"alphaPrice":0.003592991,"marketCap":15477.730864984,"validators":13,"miners":1,"realRevenueSignal":0.103515625,"signalSource":"computed:v1-low-confidence","registeredAtBlock":3212175},{"uid":38,"name":"colosseum","emissionShare":0.04362898041433647,"alphaPrice":0.017043475,"marketCap":16212.829420191,"validators":11,"miners":1,"realRevenueSignal":0.5024820005053051,"signalSource":"computed:v1","registeredAtBlock":7284230},{"uid":39,"name":"deprecated","emissionShare":0,"alphaPrice":0.006431763,"marketCap":25871.054242358,"validators":10,"miners":240,"realRevenueSignal":0.546875,"signalSource":"computed:v1-low-confidence","registeredAtBlock":3280104},{"uid":40,"name":"Chunking","emissionShare":0,"alphaPrice":0.003186467,"marketCap":13317.46566445,"validators":13,"miners":1,"realRevenueSignal":0.103515625,"signalSource":"computed:v1-low-confidence","registeredAtBlock":3372582},{"uid":41,"name":"Almanac","emissionShare":0.015843911302508694,"alphaPrice":0.006183274,"marketCap":25758.128838612,"validators":10,"miners":27,"realRevenueSignal":0.130859375,"signalSource":"computed:v1-low-confidence","registeredAtBlock":3394182},{"uid":42,"name":"Unknown","emissionShare":0,"alphaPrice":0.003334662,"marketCap":15735.893675422,"validators":10,"miners":1,"realRevenueSignal":0.080078125,"signalSource":"computed:v1-low-confidence","registeredAtBlock":3613591},{"uid":43,"name":"Graphite","emissionShare":0,"alphaPrice":0.005722434,"marketCap":26192.909352615,"validators":6,"miners":15,"realRevenueSignal":0.076171875,"signalSource":"computed:v1-low-confidence","registeredAtBlock":3408582},{"uid":44,"name":"Score","emissionShare":0,"alphaPrice":0.039219765,"marketCap":184822.131046871,"validators":9,"miners":7,"realRevenueSignal":0.083984375,"signalSource":"computed:v1-low-confidence","registeredAtBlock":3550319},{"uid":45,"name":"Talisman AI","emissionShare":0,"alphaPrice":0.00367521,"marketCap":15410.390030908,"validators":11,"miners":1,"realRevenueSignal":0.087890625,"signalSource":"computed:v1-low-confidence","registeredAtBlock":3633154},{"uid":46,"name":"Zipcode","emissionShare":0,"alphaPrice":0.011137048,"marketCap":47199.90117058,"validators":10,"miners":1,"realRevenueSignal":0.080078125,"signalSource":"computed:v1-low-confidence","registeredAtBlock":3919107},{"uid":47,"name":"EvolAI","emissionShare":0,"alphaPrice":0.005135593,"marketCap":4440.629258432,"validators":11,"miners":22,"realRevenueSignal":0.522281199764924,"signalSource":"computed:v1","registeredAtBlock":7340355},{"uid":48,"name":"Quantum Compute","emissionShare":0,"alphaPrice":0.005347819,"marketCap":23325.846860127,"validators":12,"miners":6,"realRevenueSignal":0.10546875,"signalSource":"computed:v1-low-confidence","registeredAtBlock":3856677},{"uid":49,"name":"Nepher Robotics","emissionShare":0,"alphaPrice":0.00424627,"marketCap":5695.376288137,"validators":9,"miners":2,"realRevenueSignal":0.07421875,"signalSource":"computed:v1-low-confidence","registeredAtBlock":6783158},{"uid":50,"name":"Synth","emissionShare":0,"alphaPrice":0.006805499,"marketCap":31283.757027626,"validators":12,"miners":213,"realRevenueSignal":0.509765625,"signalSource":"computed:v1-low-confidence","registeredAtBlock":4763204},{"uid":51,"name":"lium.io","emissionShare":0,"alphaPrice":0.047621926,"marketCap":192557.183971086,"validators":8,"miners":33,"realRevenueSignal":0.126953125,"signalSource":"computed:v1-low-confidence","registeredAtBlock":3966206},{"uid":52,"name":"Dojo","emissionShare":0,"alphaPrice":0.006975705,"marketCap":30318.617594311,"validators":12,"miners":1,"realRevenueSignal":0.095703125,"signalSource":"computed:v1-low-confidence","registeredAtBlock":3989825},{"uid":53,"name":"EfficientFrontier","emissionShare":0,"alphaPrice":0.0051313,"marketCap":24779.059048938,"validators":12,"miners":1,"realRevenueSignal":0.095703125,"signalSource":"computed:v1-low-confidence","registeredAtBlock":4203869},{"uid":54,"name":"Yanez MIID","emissionShare":0,"alphaPrice":0.005262065,"marketCap":24454.487222267,"validators":7,"miners":133,"realRevenueSignal":0.314453125,"signalSource":"computed:v1-low-confidence","registeredAtBlock":4742549},{"uid":55,"name":"NIOME","emissionShare":0,"alphaPrice":0.004932236,"marketCap":21861.712665959,"validators":10,"miners":11,"realRevenueSignal":0.099609375,"signalSource":"computed:v1-low-confidence","registeredAtBlock":4703386},{"uid":56,"name":"Gradients","emissionShare":0,"alphaPrice":0.019486286,"marketCap":88982.120541563,"validators":16,"miners":15,"realRevenueSignal":0.154296875,"signalSource":"computed:v1-low-confidence","registeredAtBlock":4312927},{"uid":57,"name":"Unknown","emissionShare":0.018428746236827317,"alphaPrice":0.007192108,"marketCap":3845.666338115,"validators":6,"miners":1,"realRevenueSignal":0.61953125,"signalSource":"computed:v1","registeredAtBlock":8057320},{"uid":58,"name":"Pending","emissionShare":0,"alphaPrice":0.00321561,"marketCap":12885.099549069,"validators":16,"miners":1,"realRevenueSignal":0.126953125,"signalSource":"computed:v1-low-confidence","registeredAtBlock":4367003},{"uid":59,"name":"Babelbit","emissionShare":0,"alphaPrice":0.00391202,"marketCap":18847.886079255,"validators":5,"miners":5,"realRevenueSignal":0.048828125,"signalSource":"computed:v1-low-confidence","registeredAtBlock":4401833},{"uid":60,"name":"Bitsec.ai","emissionShare":0,"alphaPrice":0.003582691,"marketCap":15748.761608991,"validators":10,"miners":2,"realRevenueSignal":0.08203125,"signalSource":"computed:v1-low-confidence","registeredAtBlock":4796992},{"uid":61,"name":"RedTeam","emissionShare":0,"alphaPrice":0.003718195,"marketCap":17026.179304174,"validators":13,"miners":7,"realRevenueSignal":0.115234375,"signalSource":"computed:v1-low-confidence","registeredAtBlock":4457976},{"uid":62,"name":"Ridges","emissionShare":0,"alphaPrice":0.013080342,"marketCap":61599.694246403,"validators":12,"miners":1,"realRevenueSignal":0.095703125,"signalSource":"computed:v1-low-confidence","registeredAtBlock":4474225},{"uid":63,"name":"Enigma","emissionShare":0,"alphaPrice":0.008565711,"marketCap":38008.494762037,"validators":9,"miners":6,"realRevenueSignal":0.08203125,"signalSource":"computed:v1-low-confidence","registeredAtBlock":4885578},{"uid":64,"name":"Chutes","emissionShare":0,"alphaPrice":0.067108337,"marketCap":346554.586896493,"validators":11,"miners":14,"realRevenueSignal":0.11328125,"signalSource":"computed:v1-low-confidence","registeredAtBlock":4531295},{"uid":65,"name":"TAO Private Network","emissionShare":0,"alphaPrice":0.003721792,"marketCap":16462.714068815,"validators":11,"miners":8,"realRevenueSignal":0.1015625,"signalSource":"computed:v1-low-confidence","registeredAtBlock":4950813},{"uid":66,"name":"ninja","emissionShare":0,"alphaPrice":0.00851618,"marketCap":36629.038746043,"validators":6,"miners":5,"realRevenueSignal":0.056640625,"signalSource":"computed:v1-low-confidence","registeredAtBlock":4958013},{"uid":67,"name":"Harnyx","emissionShare":0.025925272853353488,"alphaPrice":0.010117746,"marketCap":5054.261913414,"validators":9,"miners":1,"realRevenueSignal":0.23803226430750818,"signalSource":"computed:v1","registeredAtBlock":7236936},{"uid":68,"name":"NOVA","emissionShare":0,"alphaPrice":0.020885391,"marketCap":91051.72625805,"validators":5,"miners":3,"realRevenueSignal":0.044921875,"signalSource":"computed:v1-low-confidence","registeredAtBlock":4972413},{"uid":69,"name":"Unknown","emissionShare":0.008153025983577901,"alphaPrice":0.011847175,"marketCap":12125.713376977,"validators":8,"miners":1,"realRevenueSignal":0.62578125,"signalSource":"computed:v1","registeredAtBlock":8138182},{"uid":70,"name":"NexisGen","emissionShare":0.00431865292983944,"alphaPrice":0.004633762,"marketCap":2847.38435389,"validators":8,"miners":5,"realRevenueSignal":0.5726964060790297,"signalSource":"computed:v1","registeredAtBlock":7787562},{"uid":71,"name":"Leadpoet","emissionShare":0,"alphaPrice":0.00547949,"marketCap":23303.779462566,"validators":7,"miners":18,"realRevenueSignal":0.08984375,"signalSource":"computed:v1-low-confidence","registeredAtBlock":5048438},{"uid":72,"name":"StreetVision by NATIX","emissionShare":0,"alphaPrice":0.003285035,"marketCap":14778.958009561,"validators":6,"miners":1,"realRevenueSignal":0.048828125,"signalSource":"computed:v1-low-confidence","registeredAtBlock":5064327},{"uid":73,"name":"Parked","emissionShare":0,"alphaPrice":0.003807924,"marketCap":14000.143987895,"validators":9,"miners":1,"realRevenueSignal":0.072265625,"signalSource":"computed:v1-low-confidence","registeredAtBlock":5160047},{"uid":74,"name":"Gittensor","emissionShare":0,"alphaPrice":0.004585076,"marketCap":18610.511454668,"validators":12,"miners":49,"realRevenueSignal":0.189453125,"signalSource":"computed:v1-low-confidence","registeredAtBlock":5086205},{"uid":75,"name":"Hippius","emissionShare":0,"alphaPrice":0.019317092,"marketCap":81559.609247889,"validators":12,"miners":134,"realRevenueSignal":0.35546875,"signalSource":"computed:v1-low-confidence","registeredAtBlock":5102795},{"uid":76,"name":"Byzantium","emissionShare":0,"alphaPrice":0.004139316,"marketCap":2846.899234076,"validators":10,"miners":1,"realRevenueSignal":0.080078125,"signalSource":"computed:v1-low-confidence","registeredAtBlock":7574784},{"uid":77,"name":"Liquidity","emissionShare":0,"alphaPrice":0.00573672,"marketCap":26407.857619555,"validators":13,"miners":12,"realRevenueSignal":0.65,"signalSource":"computed:v1","registeredAtBlock":5128460},{"uid":78,"name":"Vocence","emissionShare":0.019846091379359533,"alphaPrice":0.007751557,"marketCap":3543.294499465,"validators":6,"miners":1,"realRevenueSignal":0.5612525268634655,"signalSource":"computed:v1","registeredAtBlock":7966145},{"uid":79,"name":"MVTRX","emissionShare":0,"alphaPrice":0.011841832,"marketCap":47549.30164397,"validators":7,"miners":216,"realRevenueSignal":0.4765625,"signalSource":"computed:v1-low-confidence","registeredAtBlock":5173967},{"uid":80,"name":"dogelayer","emissionShare":0,"alphaPrice":0.003146015,"marketCap":4598.47087368,"validators":11,"miners":7,"realRevenueSignal":0.099609375,"signalSource":"computed:v1-low-confidence","registeredAtBlock":7151800},{"uid":81,"name":"deprecated","emissionShare":0,"alphaPrice":0.007673757,"marketCap":29129.417122896,"validators":6,"miners":31,"realRevenueSignal":0.107421875,"signalSource":"computed:v1-low-confidence","registeredAtBlock":5203057},{"uid":82,"name":"Compelle","emissionShare":0.023447280113569644,"alphaPrice":0.009150832,"marketCap":3279.603077427,"validators":6,"miners":56,"realRevenueSignal":0.5749213101897402,"signalSource":"computed:v1","registeredAtBlock":8026517},{"uid":83,"name":"CliqueAI","emissionShare":0.02149627747864987,"alphaPrice":0.008389129,"marketCap":22219.382326271,"validators":8,"miners":248,"realRevenueSignal":0.6343409799234174,"signalSource":"computed:v1","registeredAtBlock":5231190},{"uid":84,"name":"Unknown","emissionShare":0.06740620652601328,"alphaPrice":0.026307017,"marketCap":17745.157098998,"validators":0,"miners":0,"realRevenueSignal":0.6,"signalSource":"computed:v1","registeredAtBlock":8085297},{"uid":85,"name":"Vidaio","emissionShare":0,"alphaPrice":0.007861425,"marketCap":31642.505401166,"validators":4,"miners":101,"realRevenueSignal":0.228515625,"signalSource":"computed:v1-low-confidence","registeredAtBlock":5258781},{"uid":86,"name":"⚒","emissionShare":0,"alphaPrice":0.003327081,"marketCap":4448.321853267,"validators":12,"miners":1,"realRevenueSignal":0.095703125,"signalSource":"computed:v1-low-confidence","registeredAtBlock":6914378},{"uid":87,"name":"unknown","emissionShare":0,"alphaPrice":0.003478664,"marketCap":3423.776365231,"validators":8,"miners":1,"realRevenueSignal":0.62578125,"signalSource":"computed:v1","registeredAtBlock":7208725},{"uid":88,"name":"Investing","emissionShare":0,"alphaPrice":0.003681157,"marketCap":15953.874771677,"validators":11,"miners":140,"realRevenueSignal":0.359375,"signalSource":"computed:v1-low-confidence","registeredAtBlock":5299805},{"uid":89,"name":"InfiniteHash","emissionShare":0,"alphaPrice":0.003625095,"marketCap":13317.619386768,"validators":9,"miners":2,"realRevenueSignal":0.07421875,"signalSource":"computed:v1-low-confidence","registeredAtBlock":5313364},{"uid":90,"name":"Unknown","emissionShare":0,"alphaPrice":0.003528135,"marketCap":4225.021920863,"validators":13,"miners":1,"realRevenueSignal":0.103515625,"signalSource":"computed:v1-low-confidence","registeredAtBlock":7063126},{"uid":91,"name":"Bitstarter #1","emissionShare":0.04183361848586438,"alphaPrice":0.016327016,"marketCap":9613.556130645,"validators":8,"miners":1,"realRevenueSignal":0.43183719602292747,"signalSource":"computed:v1","registeredAtBlock":7633645},{"uid":92,"name":"Unknown","emissionShare":0.04162635036826246,"alphaPrice":0.016250824,"marketCap":2068.959721114,"validators":1,"miners":1,"realRevenueSignal":0.60390625,"signalSource":"computed:v1","registeredAtBlock":8352006},{"uid":93,"name":"Bitcast","emissionShare":0,"alphaPrice":0.012624213,"marketCap":42775.151912217,"validators":9,"miners":7,"realRevenueSignal":0.083984375,"signalSource":"computed:v1-low-confidence","registeredAtBlock":5370681},{"uid":94,"name":"Bitsota","emissionShare":0,"alphaPrice":0.003665286,"marketCap":4403.966465288,"validators":11,"miners":2,"realRevenueSignal":0.08984375,"signalSource":"computed:v1-low-confidence","registeredAtBlock":6962737},{"uid":95,"name":"Actual","emissionShare":0.11920678526242506,"alphaPrice":0.046506345,"marketCap":97362.586045966,"validators":10,"miners":1,"realRevenueSignal":0.37725080287793006,"signalSource":"computed:v1","registeredAtBlock":5403674},{"uid":96,"name":"Verathos","emissionShare":0.03608185647496677,"alphaPrice":0.014081826,"marketCap":4010.692512888,"validators":7,"miners":65,"realRevenueSignal":0.2881109582064004,"signalSource":"computed:v1","registeredAtBlock":7692872},{"uid":97,"name":"Albedo","emissionShare":0.06666076082701865,"alphaPrice":0.026015157,"marketCap":18851.465967297,"validators":1,"miners":3,"realRevenueSignal":0.5587581366722567,"signalSource":"computed:v1","registeredAtBlock":7735450},{"uid":98,"name":"ForeverMoney","emissionShare":0,"alphaPrice":0.003660688,"marketCap":11057.906999488,"validators":12,"miners":1,"realRevenueSignal":0.095703125,"signalSource":"computed:v1-low-confidence","registeredAtBlock":5445992},{"uid":99,"name":"Leoma","emissionShare":0,"alphaPrice":0.004439053,"marketCap":4566.864700201,"validators":7,"miners":1,"realRevenueSignal":0.6226562499999999,"signalSource":"computed:v1","registeredAtBlock":7415113},{"uid":100,"name":"Plaτform","emissionShare":0,"alphaPrice":0.008973017,"marketCap":11806.173859324,"validators":10,"miners":1,"realRevenueSignal":0.080078125,"signalSource":"computed:v1-low-confidence","registeredAtBlock":6693448},{"uid":101,"name":"Unknown","emissionShare":0,"alphaPrice":0.00400307,"marketCap":7823.326299917,"validators":13,"miners":1,"realRevenueSignal":0.103515625,"signalSource":"computed:v1-low-confidence","registeredAtBlock":5481350},{"uid":102,"name":"ConnitoAI","emissionShare":0.039943657551784195,"alphaPrice":0.015588771,"marketCap":8650.029358048,"validators":6,"miners":5,"realRevenueSignal":0.5426865407364082,"signalSource":"computed:v1","registeredAtBlock":7840965},{"uid":103,"name":"Djinn","emissionShare":0,"alphaPrice":0.004708241,"marketCap":13744.942243515,"validators":11,"miners":245,"realRevenueSignal":0.564453125,"signalSource":"computed:v1-low-confidence","registeredAtBlock":5515448},{"uid":104,"name":"for sale (burn to uid1)","emissionShare":0,"alphaPrice":0.004100388,"marketCap":15456.791447185,"validators":1,"miners":1,"realRevenueSignal":0.009765625,"signalSource":"computed:v1-low-confidence","registeredAtBlock":5528520},{"uid":105,"name":"Beam","emissionShare":0.026570912732194397,"alphaPrice":0.010369807,"marketCap":16352.52113861,"validators":6,"miners":131,"realRevenueSignal":0.7210937500000001,"signalSource":"computed:v1","registeredAtBlock":6841399},{"uid":106,"name":"VoidAI","emissionShare":0,"alphaPrice":0.003801207,"marketCap":12810.805706502,"validators":13,"miners":1,"realRevenueSignal":0.103515625,"signalSource":"computed:v1-low-confidence","registeredAtBlock":5558480},{"uid":107,"name":"Minos","emissionShare":0.04417079661613017,"alphaPrice":0.023218807,"marketCap":17381.744844322,"validators":12,"miners":11,"realRevenueSignal":0.42814329037250165,"signalSource":"computed:v1","registeredAtBlock":7457580},{"uid":108,"name":"TalkHead","emissionShare":0,"alphaPrice":0.003640984,"marketCap":4674.556054558,"validators":11,"miners":1,"realRevenueSignal":0.087890625,"signalSource":"computed:v1-low-confidence","registeredAtBlock":7105263},{"uid":109,"name":"Academia","emissionShare":0,"alphaPrice":0.003706373,"marketCap":3468.42708758,"validators":12,"miners":1,"realRevenueSignal":0.095703125,"signalSource":"computed:v1-low-confidence","registeredAtBlock":7257480},{"uid":110,"name":"Green Compute","emissionShare":0.017456040507295226,"alphaPrice":0.008119186,"marketCap":16907.07432782,"validators":13,"miners":1,"realRevenueSignal":0.4255573971313469,"signalSource":"computed:v1","registeredAtBlock":5606062},{"uid":111,"name":"oneoneone","emissionShare":0.014446660569261341,"alphaPrice":0.005638112,"marketCap":19893.480453664,"validators":5,"miners":249,"realRevenueSignal":0.81015625,"signalSource":"computed:v1","registeredAtBlock":5615562},{"uid":112,"name":"minotaur","emissionShare":0.014382308236338603,"alphaPrice":0.005612831,"marketCap":11369.072095089,"validators":11,"miners":1,"realRevenueSignal":0.38355185812414705,"signalSource":"computed:v1","registeredAtBlock":5633022},{"uid":113,"name":"TensorUSD","emissionShare":0,"alphaPrice":0.004934951,"marketCap":5703.565776305,"validators":11,"miners":1,"realRevenueSignal":0.087890625,"signalSource":"computed:v1-low-confidence","registeredAtBlock":7119664},{"uid":114,"name":"SOMA","emissionShare":0.029342895750742736,"alphaPrice":0.011458379,"marketCap":10123.044454583,"validators":10,"miners":1,"realRevenueSignal":0.6320312499999999,"signalSource":"computed:v1","registeredAtBlock":7312241},{"uid":115,"name":"HashiChain","emissionShare":0,"alphaPrice":0.00648496,"marketCap":10912.92704538,"validators":18,"miners":1,"realRevenueSignal":0.142578125,"signalSource":"computed:v1-low-confidence","registeredAtBlock":5683635},{"uid":116,"name":"Unknown","emissionShare":0.034365719099704255,"alphaPrice":0.013411776,"marketCap":2531.455192897,"validators":5,"miners":1,"realRevenueSignal":0.6164062499999999,"signalSource":"computed:v1","registeredAtBlock":8294730},{"uid":117,"name":"Unknown","emissionShare":0,"alphaPrice":0.003616736,"marketCap":7298.820765245,"validators":1,"miners":1,"realRevenueSignal":0.009765625,"signalSource":"computed:v1-low-confidence","registeredAtBlock":5710859},{"uid":118,"name":"Ditto","emissionShare":0.04434415894137589,"alphaPrice":0.018292444,"marketCap":36597.314054281,"validators":13,"miners":1,"realRevenueSignal":0.64140625,"signalSource":"computed:v1","registeredAtBlock":5724794},{"uid":119,"name":"Satori","emissionShare":0,"alphaPrice":0.005225088,"marketCap":7886.766519422,"validators":7,"miners":1,"realRevenueSignal":0.056640625,"signalSource":"computed:v1-low-confidence","registeredAtBlock":5740660},{"uid":120,"name":"Affine","emissionShare":0,"alphaPrice":0.057657909,"marketCap":189600.006978969,"validators":9,"miners":5,"realRevenueSignal":0.080078125,"signalSource":"computed:v1-low-confidence","registeredAtBlock":5749344},{"uid":121,"name":"sundae_bar","emissionShare":0,"alphaPrice":0.005687984,"marketCap":14812.386775666,"validators":16,"miners":1,"realRevenueSignal":0.126953125,"signalSource":"computed:v1-low-confidence","registeredAtBlock":5766528},{"uid":122,"name":"Unknown","emissionShare":0.034623763908761006,"alphaPrice":0.013512674,"marketCap":3178.9341736,"validators":2,"miners":1,"realRevenueSignal":0.6070312499999999,"signalSource":"computed:v1","registeredAtBlock":8238082},{"uid":123,"name":"MANTIS","emissionShare":0,"alphaPrice":0.003758451,"marketCap":12986.460845851,"validators":7,"miners":251,"realRevenueSignal":0.544921875,"signalSource":"computed:v1-low-confidence","registeredAtBlock":5794330},{"uid":124,"name":"Swarm","emissionShare":0,"alphaPrice":0.007202139,"marketCap":22371.426460816,"validators":13,"miners":2,"realRevenueSignal":0.10546875,"signalSource":"computed:v1-low-confidence","registeredAtBlock":5813454},{"uid":125,"name":"8 Ball","emissionShare":0,"alphaPrice":0.004912784,"marketCap":13130.823678819,"validators":11,"miners":1,"realRevenueSignal":0.087890625,"signalSource":"computed:v1-low-confidence","registeredAtBlock":5834408},{"uid":126,"name":"Poker44","emissionShare":0.01591701169884619,"alphaPrice":0.006211842,"marketCap":4408.929686002,"validators":9,"miners":2,"realRevenueSignal":0.43213067313126113,"signalSource":"computed:v1","registeredAtBlock":7525773},{"uid":127,"name":"Astrid","emissionShare":0,"alphaPrice":0.003929839,"marketCap":9862.965790915,"validators":14,"miners":1,"realRevenueSignal":0.111328125,"signalSource":"computed:v1-low-confidence","registeredAtBlock":5848837},{"uid":128,"name":"ByteLeap","emissionShare":0,"alphaPrice":0.004301191,"marketCap":14774.871812103,"validators":11,"miners":23,"realRevenueSignal":0.130859375,"signalSource":"computed:v1-low-confidence","registeredAtBlock":5856038}],"events":{"registrations":[],"deregistrations":[]}}
